{
    "0": [{
            "title": "신산업 창의형 일자리 창출",
            "content": "오송오창의 바이오기술(BT)을 시작으로, 대덕의 정보통신기술(IT), 나노기술(NT), 에너지기술(ET), 세종의 스마트행정, 익산의 식품기술(FT)에 이르기까지 중원 신산업벨트를 조성하여 연구개발(R&D)과 스타트업 중심의 최첨단 클러스터로 육성<br>국민수요에 기반한 융합적 규제혁신과 지원을 통한 신산업 육성<br>- 디지털 헬스케어, 비대면 교육, K-콘텐츠 분야 등 우수인력 유입을 위한 주식매수청구권(스톡옵션) 제도 개선<br> - 스톡옵션 행사시 비과세한도 2억원으로 상향<Br>창업초기 정부 지원 확대 및 스케일업 위한 민간 투자 활성화<br> - 모태펀드 규모 2배 확대로 초기창업 및 청년/여성창업 지원 대폭 확대",
            "image": "",
            "url": "https://www.wikiyoon.com/5ba3d0f9-4e75-4bc7-a1aa-28a2137ccccd"
        },
        {
            "title": "맞춤형 일자리 정책 추진",
            "content": "급속히 변화하는 산업수요에 맞춰, 맞춤형 일자리 정책 추진<br> 20~30대를 위한 대학 창업 기지화<br>- 학생수 감소에 따른 여유 인프라를 대학창업기지로 전환하여 창업가 양성<br>- 융합교육과 창업교육과정 개설로 창업가 육성환경 마련<br>30~40대를 위한 원격근무 스마트워크를 확산, 사내 벤처 활성화<br>- 창의적이고 수평적인 스마트 조직문화로 노동생산성을 높이고 일자리 창출로 연결(특히, 여성.장애인 일자리)<br> 40~50대를 위한 디지털 역량 배가 교육<br> - 맞춤형 스마트 교육으로 다지털 역량을 배가하여 새로운 업무역량 구비<br>- ICT기반 스마트농업, 실버산업관련 교육으로 관련분야 취창업 기회확대<br> 중원 신산업벨트와 인근 대학과 연구소를 청년창업기지로 적극 활용",
            "image": "",
            "url": "https://www.wikiyoon.com/5ba3d0f9-4e75-4bc7-a1aa-28a2137ccccd"
        },
        {
            "title": "중소·중견기업의 신산업 진출 적극 지원",
            "content": "기업역량 강화와 강소기업으로 도약을 위한 ‘실질적 지원’ 강화<br>- 신산업 전환 전용 5년 거치 10년 상환 장기금융지원, R&D 지원, 투자세액공제, 혁신인력양성 확대<br>기업의 지속적인 성장을 위한 신산업 진출 뒷받침 강화<br>- 중견기업 신사업 투자에 10% 투자세액공제와 25% 연구개발 세액공제 확대로 중소기업 수준 지원 지속(피터팬 증후군 극복)<br>기업의 과도한 규제에 객관적 평가와 합리적 조정 시스템 구축<br>- 산업경쟁력에 영향을 미치는 비경제적 규제 ‘산업영향평가 실시’",
            "image": "",
            "url": "https://www.wikiyoon.com/5ba3d0f9-4e75-4bc7-a1aa-28a2137ccccd"
        },
        {
            "title": "어려운 계층 우선 지원 국민기초생활보장 생계급여 확대",
            "content": "국민기초생활보장 생계급여 지급기준을 기준 중위소득 30%에서 35%로 2022년 하반기부터 상향 조정. 약 21만명이 추가로 혜택을 볼 수 있을 것으로 예상<br>국민기초생활보장제도의 재산소득환산제에 ‘재산 컷오프제’를 도입하여 빈곤층의 소득지원을 확대<br>장애인, 노인, 아동을 비롯한 근로능력이 없는 가구원이 있는 경우에 개인별 월 10만원의 추가 지급을 실시하고, 소득인정액에서 제외하여 생활비 지원을 현실화. 총 85만명이 추가로 혜택을 볼 수 있을 것으로 예상",
            "image": "",
            "url": "https://www.wikiyoon.com/5ba3d0f9-4e75-4bc7-a1aa-28a2137ccccd"
        },
        {
            "title": "워킹푸어 소득 증대를 위해 근로장려세제 확충",
            "content": "워킹푸어(일해도 어려운 근로빈곤층)를 위해 기존 근로장려세제(EITC)의 소득기준을 최대 20%로 높이고 재산 요건을 완화해, 워킹푸어가 탈빈곤할 수 있도록 지원. 이를 통해 약 113만가구가 추가로 혜택을 볼 수 있을 것으로 예상<br>기초생활보장 수급자의 급여액 결정 시 근로 및 사업 소득에 대한 공제를 50%까지 확대",
            "image": "https://oopy.lazyrockets.com/api/v2/notion/image?src=https%3A%2F%2Fs3-us-west-2.amazonaws.com%2Fsecure.notion-static.com%2Fab9384a2-260a-4864-8e55-945b1e700d46%2FUntitled.png&blockId=3a0a90cd-7703-43f6-9f30-27b1089c1e0c",
            "url": "https://www.wikiyoon.com/5ba3d0f9-4e75-4bc7-a1aa-28a2137ccccd"
        },
        {
            "title": "긴급복지지원제도 -> 전 국민안심지원제도",
            "content": "그동안 정부는 국민기초생활보장제도의 사각지대를 줄이기 위해 취약계층을 대상으로 긴급복지지원제도를 운영해왔음. 하지만 독거노인, 청년단독가구, 조손가구, 한부모가구 등을 중심으로 발생하는 예측불가 위기상황에 신속하게 대응하여 지원하기에는 여전히 미비하다는 지적이 많았음. 더구나 지금은 취약계층 뿐 아니라 서민과 중산층까지 위기를 느끼는 비상상황임<br>이에 따라 모든 국민을 위기 상황 및 생애 특수상황으로부터 보다 적극적으로 보호, 지원하기 위해 현행 긴급복지지원제도를 국민안심지원제도로 확대·개편하고자 함<br>긴급복지지원 선정에서 문제로 지적되는 ‘위기사유’를 확대. 가구주 사망, 실직, 이혼, 질병 등 개인의 생애 특수상황으로 생계가 어려운 가구에 대해 충분하고 적절한 지원이 신속하고 유연하게 이루어질 수 있도록 하겠음<br>구체적으로는, 지원액 선정 기준이 되는 주거용 재산 기준을 폐지하고 금융 재산 기준을 확대해 기존 제도보다 훨씬 많은 국민이 혜택을 볼 수 있도록 하겠음. 또 지원 액수를 현행 중위소득의 약 26%에서 개편후 40% 수준으로 올리고, 지원 기간도 현행 1개월에서 3개월로 연장하겠음<br>신속한 지원을 위해 선지원·후심사 원칙을 견지하고, 복지 담당 현장 공무원들의 재량권과 면책을 확대하겠음<br>단, 2년에 1회 제도를 활용할 수 있도록 제한하고, 후심사에서 문제가 발견되면 다음에 다시 제도를 이용할 때 불이익을 주는 방식으로 도덕적 해이를 방지하겠음",
            "image": "",
            "url": "https://www.wikiyoon.com/5ba3d0f9-4e75-4bc7-a1aa-28a2137ccccd"
        },
        {
            "title": "사회복지종사자의 처우개선",
            "content": "① 사회복지종사자 단일임금체계 도입<br>임금 격차에 따른 형평성 문제 해결 및 낮은 급여체계 개선<br>국고지원시설과 지방이양시설의 개별 인건비 가이드라인을 '사회복지시설 종사자 인건비 가이드라인’ 맞춰 일원화<br>② 사회복지종사자 안전 확보 및 인권보호<br>신변안전과 인권보호, 폭력에 대한 실효적 피해구제 위해 현행 사회복지사법 등에 제도적 장치 마련<br>③ 사회복지연수원 설치<br>지역별 유휴시설 등을 활용해 사회복지종사자의 역량 강화와 치유 및 회복지원",
            "image": "https://oopy.lazyrockets.com/api/v2/notion/image?src=https%3A%2F%2Fs3-us-west-2.amazonaws.com%2Fsecure.notion-static.com%2F33982e5f-dbda-42e1-b823-5cc001034061%2FUntitled.png&blockId=0f97e0fb-fcad-4b39-8b32-b5f2705e69d0",
            "url": "https://www.wikiyoon.com/5ba3d0f9-4e75-4bc7-a1aa-28a2137ccccd"
        },
        {
            "title": "연말정산 : 2천만 월급쟁이 등 세금부담 완화",
            "content": "봉급생활자 등 세금 부담 연 3조원 경감<br>인적공제 본인 기본공제액 상향 조정(현행 1인당 150만원 → 200만원)<br>부양가족 요건 완화 (현행 만 20세 이하 → 만 25세 이하)<br>부양가족 인적공제 배제기준 상향 조정(현행 연소득 100만원 이하 → 200만원 이하, 근로소득 총 급여액 500만원 이하 → 700만원 이하)<br> 봉급생활자 등 세금 부담 연 1200억원 경감<br>신용카드 등 사용액 공제 한도 50% 인상<br>코로나 끝날 때까지 음·숙박, 유류비, 교통비 지출액 공제율 지금 2배!",
            "image": "https://oopy.lazyrockets.com/api/v2/notion/image?src=https%3A%2F%2Fs3-us-west-2.amazonaws.com%2Fsecure.notion-static.com%2Fd093eb20-ae6d-4119-9961-993a42ea6c56%2FUntitled.png&blockId=96161670-6956-44b7-954b-1ba3a495c377",
            "url": "https://www.wikiyoon.com/5ba3d0f9-4e75-4bc7-a1aa-28a2137ccccd"
        }
    ],
    "1": [{
            "title": "개인투자자에 대한 세제 지원 강화",
            "content": "주식양도소득세 폐지<br>증권거래세 적정 수준으로 유지",
            "image": "",
            "url": "https://www.wikiyoon.com/dcf4e4ad-ac57-473a-a947-4c2e57176dd0"
        },
        {
            "title": "신사업 분할 상장 시 투자자 보호 강화",
            "content": "신사업을 분할하여 별도 회사로 상장하는 경우 모회사 주주에 신주인수권 부여할 수 있도록 관련 규정 정비<br>자회사 공모주 청약 시 원래 모회사 주주에게 일정 비율을 공모가로 청약하는 방식으로 신주인수권 부여가 가능",
            "image": "",
            "url": "https://www.wikiyoon.com/dcf4e4ad-ac57-473a-a947-4c2e57176dd0"
        },
        {
            "title": "내부자의 무제한 지분 매도 제한",
            "content": "공매도에 있어 개인투자자가 외국인 및 기관투자자에 비해 불리하지 않도록 제도 개선<Br> 기관에 비해 높은 담보비율 등을 합리적으로 조정<br>주가하락 과도할 경우 자동으로 공매도가 금지되는 공매도 서킷브레이크 도입 적극 검토",
            "image": "",
            "url": "https://www.wikiyoon.com/dcf4e4ad-ac57-473a-a947-4c2e57176dd0"
        },
        {
            "title": "자본시장의 투명성과 공정성 획기적 개선",
            "content": "회계와 공시의 투명성 제고, 자본시장 투명성의 기초를 확립<br>미공개 정보이용, 주가조작 등 증권범죄의 수사 및 처벌에 이르는 전 과정 개편하여 제재의 실효성 강화",
            "image": "",
            "url": "https://www.wikiyoon.com/dcf4e4ad-ac57-473a-a947-4c2e57176dd0"
        },
        {
            "title": "주식 공매도 감시 전담 조직 설치 및 불법 공매도 엄정 처벌",
            "content": "무차입 공매도 여부를 매일 실시간 점검, 불법 공매도 적발시 주가조작에 준하는 형사처벌",
            "image": "https://oopy.lazyrockets.com/api/v2/notion/image?src=https%3A%2F%2Fs3-us-west-2.amazonaws.com%2Fsecure.notion-static.com%2F06215b37-e587-412f-ab2f-7789964e0a15%2FUntitled.png&blockId=588a81bb-996b-4dcd-9fa0-a13b0aadfcce",
            "url": "https://www.wikiyoon.com/dcf4e4ad-ac57-473a-a947-4c2e57176dd0"
        },
        {
            "title": "주식 상장폐지의 요건 정비 및 상장폐지 과정의 단계별 관리체계 확대",
            "content": "수익성 등 상장 지속성에도 불구하고 전격 상장폐지 되지 않도록 요건을 강화<br>세분화 단계에 의한 관리종목 지정, 장외거래소로 이관 등 상장폐지 전단계 관리체계를 확대",
            "image": "https://oopy.lazyrockets.com/api/v2/notion/image?src=https%3A%2F%2Fs3-us-west-2.amazonaws.com%2Fsecure.notion-static.com%2F06215b37-e587-412f-ab2f-7789964e0a15%2FUntitled.png&blockId=588a81bb-996b-4dcd-9fa0-a13b0aadfcce",
            "url": "https://www.wikiyoon.com/dcf4e4ad-ac57-473a-a947-4c2e57176dd0"
        },
        {
            "title": "주식 물적 분할 요건 강화 및 주주 보호대책 제도화",
            "content": "분할 자회사 상장 제한, 상장시 주식을 모회사 주주에게 배정하는 방안 등 보호대책 수립",
            "image": "https://oopy.lazyrockets.com/api/v2/notion/image?src=https%3A%2F%2Fs3-us-west-2.amazonaws.com%2Fsecure.notion-static.com%2F06215b37-e587-412f-ab2f-7789964e0a15%2FUntitled.png&blockId=588a81bb-996b-4dcd-9fa0-a13b0aadfcce",
            "url": "https://www.wikiyoon.com/dcf4e4ad-ac57-473a-a947-4c2e57176dd0"
        },
        {
            "title": "코인 투자 수익 5천만원까지 완전 비과세",
            "content": "현행 250만원인 양도차익 기본공제를 주식과 동일하게 상향<br>선(先)정비·후(後)과세 원칙 유지",
            "image": "https://oopy.lazyrockets.com/api/v2/notion/image?src=https%3A%2F%2Fs3-us-west-2.amazonaws.com%2Fsecure.notion-static.com%2Ff980c911-9ed4-479a-8c8a-373deb478e68%2FUntitled.png&blockId=7131f063-1ba7-4a8b-8572-0a8c62b1e136",
            "url": "https://www.wikiyoon.com/8e46e547-f2d0-496a-bd95-bd52b21b2ab7"
        },
        {
            "title": "‘디지털자산 기본법’ 제정 및 디지털산업진흥청 설립",
            "content": "코인 부당거래 수익, 사법절차를 거쳐 전액 환수<br>디지털자산거래계좌와 은행을 연계시키는 전문금융기관 육성",
            "image": "https://oopy.lazyrockets.com/api/v2/notion/image?src=https%3A%2F%2Fs3-us-west-2.amazonaws.com%2Fsecure.notion-static.com%2Ff980c911-9ed4-479a-8c8a-373deb478e68%2FUntitled.png&blockId=7131f063-1ba7-4a8b-8572-0a8c62b1e136",
            "url": "https://www.wikiyoon.com/8e46e547-f2d0-496a-bd95-bd52b21b2ab7"
        },
        {
            "title": "국내 코인발행(ICO) 허용, 거래소발행(IEO) 방식부터 시작",
            "content": "안전장치 마련된 거래소발행(IEO: Initial Exchange Offering) 방식부터 도입할 계획",
            "image": "https://oopy.lazyrockets.com/api/v2/notion/image?src=https%3A%2F%2Fs3-us-west-2.amazonaws.com%2Fsecure.notion-static.com%2F4bf38dee-8415-4040-bc00-a3a0a32a65c4%2FUntitled.png&blockId=551e86a2-5c51-4b54-a66a-1b3fb7f23479",
            "url": "https://www.wikiyoon.com/8e46e547-f2d0-496a-bd95-bd52b21b2ab7"
        },
        {
            "title": "NFT 활성화를 통한 신개념 디지털자산시장 육성",
            "content": "블록체인 기반 기술개발 지원 및 제도적 기반 선제적 마련<br>디지털자산을 보호하기 위한 법적 기반 구축<br>기술개발에 장애가 되는 걸림돌 제거 위해 네거티브 규제 시스템 도입",
            "image": "https://oopy.lazyrockets.com/api/v2/notion/image?src=https%3A%2F%2Fs3-us-west-2.amazonaws.com%2Fsecure.notion-static.com%2F4bf38dee-8415-4040-bc00-a3a0a32a65c4%2FUntitled.png&blockId=551e86a2-5c51-4b54-a66a-1b3fb7f23479",
            "url": "https://www.wikiyoon.com/8e46e547-f2d0-496a-bd95-bd52b21b2ab7"
        }


    ],
    "2": [{
            "title": "확고한 주택공급 정책",
            "content": "수요에 부응하는 주택의 공급에 주력하되 시장 안정을 위해 필요한 경우 추가적인 공공택지의 단계적 개발도 고려",
            "image": "",
            "url": "https://www.wikiyoon.com/69ca5d97-10c1-453b-8b8f-901c6bcdcbd4"
        },
        {
            "title": "5년간 250만 호 이상 공급",
            "content": "수도권 130만호 이상 최대 150만호<br><Br>재건축 ‧ 재개발 47만 호(수도권 31만 호) : 정밀안전진단 기준 합리화, 재건축초과이익 부담금 완화, 신속 통합 인허가, 용적률 인센티브 등 제도개선을 통해 공급물량 20~30% 확대<br>도심 ‧ 역세권 복합개발 20만 호(수도권 13만 호) : 도심 복합개발혁신지구 제도를 도입하여 도심지역, 역세권, 준공업지역 등 복합개발<br>국공유지 및 차량기지 복합개발 18만 호(수도권 14만 호) : 차량기지와 지상 전철부지, 그리고 미활용 국공유지를 복합‧입체화 개발 추진<br>소규모 정비사업 10만호(수도권 7만호) : 기반시설 설치, 용적률 인센티브, 인·허가 절차 간소화 등을 통해 소규모로 주택공급<br>공공택지 142만 호(수도권 74만 호) : 현재 개발 중인 공공택지 및 GTX A~D 노선상의 역세권 콤팩트시티 건설 추진<br><br>기타 13만 호(수도권 12만 호) : 서울 상생주택, 매입약정 민간개발 등",
            "image": "",
            "url": "https://www.wikiyoon.com/69ca5d97-10c1-453b-8b8f-901c6bcdcbd4"
        },
        {
            "title": "공공임대주택의 양적, 질적 확충",
            "content": "공공임대주택에는 ▲공공이나 민간이 지어서 임대하는 건설임대주택 ▲기존 건물을 매입해서 임대하는 매입임대주택 등이 있음. 현재 장기공공임대주택 재고량은 전체 주택의 7.4%를 차지하지만(2019년 기준), 이중 시설이 열악한 매입임대주택이나 면적이 작은 행복주택을 중심으로 수요자가 외면하는 공실이 발생하고 있음<br>윤석열 정부는 ‘살고 싶은 곳에, 살고 싶은 집을 지어주는 정책’으로 공공임대주택의 방향을 잡겠음. 수요가 높은 건설임대를 중심으로 공공임대주택을 연 평균 10만호씩 50만호 공급하겠음. 수요자들의 욕구에 맞춰 호당 면적 규모도 확대하고, 도심복합개발 등을 통해 수요가 있는 곳에 공급하겠음<br>기존 노후 공공임대주택의 복합개발과 리모델링도 추진하겠음. 현재, 공급된지 30년 넘는 장기공공임대주택에서 건물 노후화로 입주자 기피 현상이 발생하고 있음. 노후 공공임대주택 복합개발과 리모델링을 통해 이같은 문제를 해결하고 주거취약계층의 삶의 질을 현저히 개선하겠음<br>민간임대주택 사업자에 세금 감면 혜택을 부여하는 대신, 공급량의 30%를 시장가격의 2/3 이하 임대료를 받고 주거취약계층에 제공하도록 하겠음. 이를 통해 여러 계층이 쾌적한 환경에서 차별이나 구별 없이 섞여 사는 사회적 혼합(social mix)을 실현하겠음",
            "image": "",
            "url": "https://www.wikiyoon.com/6c70358b-c835-4df9-b242-89ec80e3bd79"
        },
        {
            "title": "비정상 거처 거주자의 완전 해소",
            "content": "전체 가구의 3.7% 정도(2020년 주거실태조사)가 비정상 거처(공장, 여관, 판자집, 비닐하우스, 고시원 등)에 거주하고 있어 인간다운 삶을 영위할 수 없는 상태임<br>임대보증금을 무이자로 대여하여 정상 거처로 이전하겠음<br>주거급여 외에 정상 거처 이전 조건부 바우처를 지급해, 주거취약계층이 이사비 부담을 느끼지 않도록 조치하겠음",
            "image": "",
            "url": "https://www.wikiyoon.com/6c70358b-c835-4df9-b242-89ec80e3bd79"
        },
        {
            "title": "주거급여 대상 확대 및 급여 현실화",
            "content": "주거급여 대상자가 2015년 제도 도입 당시 기준중위소득의 43%에서 2022년 46%로 확대되었으나, 아직 상대적 빈곤선인 기준중위소득의 50% 수준에는 못미친 상태이고, 급여 수준도 최저주거기준을 충족시키기에 부족한 상태임<br>주거급여 대상자를 기준중위소득 46%에서 50%로 확대하겠음<br>주거급여 기준이 되는 기준임대료를 100% 현실화하고, 기준임대료의 지역별 기준(현행 4개 급지)을 세분화하여 현실에 맞게 기준임대료를 설정하여 급여를 현실화하겠음<br>기후변화를 감안하여 혹서기 지원을 신설하고, 주거비의 일부라고 할 수 있는 관리비도 주거급여의 일부로 산정하겠음 (생계급여와의 역할 조정)<br> 최저주거기준 미달가구에게는 이사비 바우처를 지급하겠음<br> 청년 1인가구 분리 기준 연령(현행 30세)을 낮춰 청년 1인 가구도 주거급여 지급대상이 되도록 개선하겠음",
            "image": "",
            "url": "https://www.wikiyoon.com/6c70358b-c835-4df9-b242-89ec80e3bd79"
        },
        {
            "title": "2022년 주택 공시가격을 2020년 수준으로 환원",
            "content": "한해 공시가격을 19%나 올리는 나라는 없음<br>공시가격을 환원하지 않으면 윤석열 정부는 관련법 시행령을 개정하여 공정시장 가액비율을 인하",
            "image": "",
            "url": "https://www.wikiyoon.com/a2e494c1-1602-4c71-8e94-84b048605740"
        },
        {
            "title": "종합부동산세와 재산세와 통합",
            "content": "종부세를 폐지하여 지방세인 재산세와 통합<br>통합 이전이라도 세 부담 완화 조치 실시<br>- 내년에 100%로 인상될 예정인 공정시장가액 비율을 현 수준인 95%에 동결<br>- 50%에서 200%에 이르는 세부담 증가율 상한을 인하<br> - 1 주택자에 대한 세율은 이 정부 이전 수준으로 인하<br>- 일정 소득 이하 1주택 장기 보유자에 대해서는 연령에 관계없이 종부세를 매각/상속 시점까지 이연납부 허용<br>- 차등과세 기준을 보유주택 호수에서 가액으로 전환",
            "image": "",
            "url": "https://www.wikiyoon.com/a2e494c1-1602-4c71-8e94-84b048605740"
        },
        {
            "title": "양도소득세 개편",
            "content": "다주택자에 대한 중과세율 적용을 한시적으로 최대 2년간 배제하여 다주택자의 보유 주택 매각을 촉진",
            "image": "",
            "url": "https://www.wikiyoon.com/a2e494c1-1602-4c71-8e94-84b048605740"
        },
        {
            "title": "취득세 부담 인하",
            "content": "현재 1~3%인 1 주택자에 대한 취득세율을 단일화 하거나 세율 적용 구간을 단순화<br>단순누진세율을 초과누진세율로 변경<br>생애 최초 구입자에 대해서는 취득세를 면제하거나 1% 단일 세율을 적용<br>조정지역 2주택 이상에 대한 과도한 누진세율 완화",
            "image": "",
            "url": "https://www.wikiyoon.com/a2e494c1-1602-4c71-8e94-84b048605740"
        },
        {
            "title": "부동산세제 정상화를 위해 정부 출범 즉시 TF 가동",
            "content": "충분한 연구와 공론화를 거쳐 종합적인 개편 방안을 마련",
            "image": "",
            "url": "https://www.wikiyoon.com/a2e494c1-1602-4c71-8e94-84b048605740"
        },
        {
            "title": "용적율 상향 조절·규제 완화",
            "content": "1기 신도시 재정비 사업은 ‘국민이 살고 싶어 하는 동네에 살고 싶은 주택을 충분히 공급해 부동산 시장을 안정시킨다’는 부동산 대책의 틀 안에 있음1기 신도시 재정비 특별법 만들어 용적률 상향 등 행정 절차 신속 진행. 1기 신도시는 평균 용적률 169~226%로 건설됐는데, 토지용도 변경과 종·상향을 통해 용적률을 추가하고 체계적으로 재정비사업을 추진하면 10만 호 이상을 추가공급할 수 있음. 3기 신도시 2~3개 새로 짓는 것과 맞먹는 분량<br>다양한 규제 완화 통해 사업의 수익성 개선하고 주민의 부담 덜어줄 계획",
            "image": "https://oopy.lazyrockets.com/api/v2/notion/image?src=https%3A%2F%2Fs3-us-west-2.amazonaws.com%2Fsecure.notion-static.com%2F4e8dd37d-b562-40f1-9429-d7a9b2ee6983%2FUntitled.png&blockId=34bd589c-91ee-4e27-b564-0ccfad3bfaff",
            "url": "https://www.wikiyoon.com/f1efa7db-9da7-4446-aefa-a9fb4858e2d0"
        },
        {
            "title": "세입자도 득을 보는 재정비 사업",
            "content": "지금까지 재건축·리모델링 사업은 집주인만 득을 보고 세입자에겐 큰 혜택 없었음. 이를 해결하기 위해 △자금 부담 능력이 부족한 고령 가구에게 재정비 기간 중 이주할 주택 제공, △세입자들이 재정착할 수 있도록 일반분양분 우선 청약권과 임대주택 입주 기회 제공",
            "image": "https://oopy.lazyrockets.com/api/v2/notion/image?src=https%3A%2F%2Fs3-us-west-2.amazonaws.com%2Fsecure.notion-static.com%2F4f2eaae9-c0ad-45b6-9044-c3b371929a4e%2FUntitled.png&blockId=7162d306-c2b6-407a-abf7-1d37d757cb79",
            "url": "https://www.wikiyoon.com/f1efa7db-9da7-4446-aefa-a9fb4858e2d0"
        },
        {
            "title": "이주전용단지 만들어 이사 수요 조절",
            "content": "재정비 과정에서 이사 수요가 한꺼번에 쏟아져 집값이 들썩이거나 주민들이 불편을 겪지 않도록 1기 이주전용단지를 만들어 순환개발을 실시<br>이주전용단지 부지로는 3기 신도시 개발예정지역을 포함한 중소 규모 공공택지개발사업지구가 꼽히고 있음. 3기 신도시 청약 대기자와 입주 희망자들에게 피해가 없도록, 택지공급 순위 자체를 늦춘 후순위 부지와 임대주택부지, 미분양 토지, 중·소규모 공공택지 활용 방식. 이주전용단지로 쓰임새가 다하면, 88올림픽 아파트처럼 공공임대주택이나 분양주택으로 활용",
            "image": "https://oopy.lazyrockets.com/api/v2/notion/image?src=https%3A%2F%2Fs3-us-west-2.amazonaws.com%2Fsecure.notion-static.com%2F7b6a0ea1-0b82-41e9-877e-ac1be166b25b%2FUntitled.png&blockId=4bed4a3e-772c-44b0-b348-8ab2634cd008",
            "url": "https://www.wikiyoon.com/f1efa7db-9da7-4446-aefa-a9fb4858e2d0"
        }


    ],
    "3": [{
            "title": "수도권 도심 철도 지하화",
            "content": "- 도심 철도는 지역의 단절, 주변 지역의 낙후, 환경 악화의 원인으로, 지하화는 오랜 기간 숙원사업. 도심 철도 지하화 통해 도심지역을 미래형 도시로 재창조- 지하화 범위는 경부선의 당정~서울역 구간(32km, 19개역 포함), 경인선의 구로~도원역 구간(22.8km, 19개역 포함), 경원선의 청량리~도봉산 구간(13.5km, 11개역 포함)- 지하화로 생기는 상부 토지에는 주거와 업무공간, 주민 편의시설, 녹지 생태 공간 조성. 도시 공간이 새롭게 개발되면 20만 일자리 창출 효과*도 기대<br>- 공법은 대심도 Shield TBM 공법을 적용하여 지상 교통 차단없이 공사를 진행할 수 있도록 할 계획. 총 사업비는 23조 8550억원(경부선 16조 700억, 경인선 4조 7340억, 경원선 3조 510억). 지상권 개발이익 18조 1,400억이고 부족한 재원 5조 7천억원 정도는 정부의 직접 개발 사업으로 충당할 예정",
            "image": "",
            "url": "https://www.wikiyoon.com/2720f68b-732e-44a2-af7f-e678193aaba5"
        },
        {
            "title": "경부고속도로 양재~한남IC 구간 지하화",
            "content": "- 양재∼한남IC 구간으로 인한 강남지역 동서단절과 이 구간의 만성정체에 따른 고속도로 기능상실 보완을 위해 경부간선 양재~한남IC 구간 약 6.8km를 최소 필요도로(2~4차선)만 남긴 채 모든 도로를 지하터널화 하는 경부고속도로 지하화 적극 추진<br>- 양재~한남IC 구간 지하화하면 기존 노면과 완충녹지 등 합쳐 여의도공원 면적의 약 3배인 60만㎡ 공원 면적 확보. 지상 공원에는 각종 문화시설이 들어서고 단절된 강남을 하나로 잇는 역할 할 것<br>- 예상 사업비 3조 3천억원은 도로 지하화로 생기는 지상에 쇼핑ㆍ복합시설 등의 개발 통해 얻는 수익으로 충당할 예정<br>- 이로써 40여년전 개통 당시보다 100배 가까이 늘어난 경부고속도로의 교통량과 환경까지 고려하여 주민 편의 획기적으로 개선할 예정",
            "image": "",
            "url": "https://www.wikiyoon.com/2720f68b-732e-44a2-af7f-e678193aaba5"
        },
        {
            "title": "신분당선 서울 서북부(용산~삼송)까지 연장",
            "content": "신분당선 서울 서북부(용산~삼송)까지 연장<br> - 신분당선 서울지역 연장사업이 신사역~용산역까지 되어있는 것을 용산역에서 서울역을 잇고 은평뉴타운을 거쳐 삼송역까지 연장할 예정<br>- 이를 통해 서울 종로, 은평, 경기 고양 등 서울 서북부 지역의 교통난과 출퇴근 불편을 해소",
            "image": "",
            "url": "https://www.wikiyoon.com/2720f68b-732e-44a2-af7f-e678193aaba5"
        },
        {
            "title": "1기 GTX 노선 연장",
            "content": "정부는 2027년 완공 목표로 2019년 1기 GTX 3개 노선 일부 착공. 운정과 동탄 잇는 A노선(2019년 착공), 송도와 마석 잇는 B노선(2023년 착공 예정), 덕정과 수원 잇는 C노선(2022년 착공 예정)이들 3개 노선은 수도권 전체 아우르기엔 역부족. 교통사각 지대가 많이 남기 때문에, 혜택을 보지 못하는 주민이 여전히 많음. 이런 상황에서 3기 신도시 포함한 대규모 개발사업이 속속 완성되면, 1기 GTX 노선이 닿지 않는 지역 중심으로 심각한 교통지옥이 벌어짐<br>우선 1기 GTX A 노선과 C 노선 연장. A 노선은 기존 운정~동탄에서 운정~동탄~평택까지, C 노선은 기존 덕정~수원에서 동두천~덕정~수원~평택까지 연장",
            "image": "",
            "url": "https://www.wikiyoon.com/2720f68b-732e-44a2-af7f-e678193aaba5"
        },
        {
            "title": "2기 GTX 3개 노선 추가해 수도권을 하나의 메가시티로",
            "content": "2기 GTX 3개 노선 추진 계획- D 노선 수도권 남부에서 동·서 이음. 김포~부천종합운동장~신림~사당~삼성~하남~팔당 라인을 기본으로, 삼성에서 분기되어 삼성~수서~광주~여주 잇는 라인을 추가해 옆으로 눕힌 Y자 형태로 건설. 김포~부천종합운동장 구간과 인천국제공항~부천종합운동장 구간을 Y자 형태로 신설, 부천종합운동장~팔당 구간 신설, 삼성~여주 구간 신설 및 기존 경강선 일부 활용- E 노선 수도권 북부에서 동·서 이음. 인천~김포공항~정릉~구리~남양주 연결. 김포공항~구리 구간은 신설하고 나머지 구간은 공항철도와 경의 중앙선을 활용. 지금까지 수도권 북부는 동·서 잇는 철도망이 없었음. E 노선이 생기면 북부지역 발전이 탄력 받게 됨- F 노선 수도권 거점지역을 연결해 수도권 전체를 하나의 메가시티로 묶는 순환선. 고양~안산~수원~용인~성남~하남~의정부~고양을 잇는 라인으로, 성남~고양 구간만 신설하고 나머지는 서해선과 수인 분당선 등 활용<br>기존 1기 GTX 3개 노선이 연장되고 2기 GTX 3개 노선까지 완공되면, 1기 신도시 5곳, 2기 신도시 10곳, 3기 신도시 5곳 등 수도권 일대 주요 주거 밀집지역에서 서울 도심까지 소요시간 획기적으로 줄어듬. 서울과 수도권이 뉴욕, 도쿄, 런던 같은 세계적 메트로폴리스보다 훨씬 빠른 광역 교통망 갖추게 될 것",
            "image": "",
            "url": "https://www.wikiyoon.com/2720f68b-732e-44a2-af7f-e678193aaba5"
        },
        {
            "title": "GTX 노선따라 콤팩트시티 건설해 총 25만호공급",
            "content": "1기·2기 GTX 차량기지 입체화, 노선 주변에 일정 규모의 부지 확보해 2030이 살기 좋은 1만~2만호 규모의 역세권 콤팩트 시티 다수 조성할 계획우선 1기 GTX 3개 노선의 차량기지와 주요 정차장 주변 재정비해 3만호, 기존 C노선의 연장구간 정차역 주변 도시개발사업과 연계해 2만호 공급<br>이어 2기 GTX D 노선, E 노선과 F 노선의 주요 정차역과 차량기지 4개소 이용하여 20만호 공급 예정",
            "image": "",
            "url": "https://www.wikiyoon.com/2720f68b-732e-44a2-af7f-e678193aaba5"
        },
        {
            "title": "수도권 버스·지하철 노선, 실핏줄처럼 보강",
            "content": "1기 GTX 노선 연장하고 2기 GTX 3개 노선 새로 만드는 한편, 경기도 지자체들과 협의해 기존 버스와 지하철 노선이 GTX 주요 정차역 사이사이를 실핏줄처럼 채울 수 있도록 대중교통망 보강 계획<br><br>1기 GTX 노선 연장하고 2기 GTX 3개 노선 신설하는데 소요되는 재원 총 17조 6,440억 원. 윤석열 정부는 이중 3조~4조원을 국비로 보조하고, 나머지 금액은 민간자본투자와 역세권 콤팩트시티 개발수익으로 충당 계획",
            "image": "",
            "url": "https://www.wikiyoon.com/2720f68b-732e-44a2-af7f-e678193aaba5"
        }

    ],
    "4": [{
            "title": "코로나 백신 인과관계 증명책임 및 안전한 백신 확보",
            "content": "1.코로나 백신 부작용 인과관계 증명책임, 정부가 부담<br>백신 접종은 자발적인 행위라기보다 국가공동체의 필요에 따라 이루어지는 공공정책<br>관련법과 제도를 개선해 인과성 증명에 대한 국민부담 없앨 것<br> 2.선보상 후정산(사망자), 선치료 후보상(중증환자)<br>3.부작용과 이상반응 수집, 조사 및 역학적 연구 확대<br>백신 부작용 피해자 보상절차 체계화 위한 ‘백신부작용 국민신고센터’ 설치·운영<br>4.세계적으로 안전성 입증된 우수한 백신 확보",
            "image": "",
            "url": "https://www.wikiyoon.com/1855325a-76c8-4603-ad5b-aa1681afc74e"
        },
        {
            "title": "코로나 중증환자 병상 확보",
            "content": "1.병상확보를 위해 공공의료기관을 전담병원으로 전환하고 긴급 임시병동을 마련<br>국립의료원 등을 중환자전담병원으로 신속히 전환, 모든 병상 투입<br>다른 공공의료기관도 감염병 전담병원으로서의 기능을 강화. 2015년 메르스사태 때처럼 모든 병동을 비워 코로나 중환자 치유에 집중<br>전문병동의 부족에 대비하여 예비비를 투입해서라도 공공건물을 개조하거나 긴급임시병동을 신축하여 병상 확보<br>2. 확진환자에 대한 재택치료원칙을 전면 개편<br> 만성질환자 고령자는 경증이라도 반드시 입원치료를 받도록 할 것<br>무증상이며 건강한 성인의 경우 일선 의원급 그리고 민간의료기관의 코로나19 외래 치료를 확대하여 조기에 치료가 가능하도록 의료체계를 정상화할 것<br>3. 자가 승용차를 포함한 코로나19 환자 이송체계를 전면 확대 밎 개편<br> 4. 실내 바이러스 저감장치의 설치 운영을 지원하여 코로나19 감염위험을 낮출 것<br>노인요양기관, 학생학습공간, 자영업, 소상공인에게 헤파필터 공기청정살균기, 외부공기순환기 등을 보급 설치 운영하게 할 것<br>긴급한 돌봄을 담당하는 기관의 운영, 소상공인의 생계 영업, 그리고 학생들의 중단없는 학습권을 보장",
            "image": "",
            "url": "https://www.wikiyoon.com/1855325a-76c8-4603-ad5b-aa1681afc74e"
        },
        {
            "title": "코로나 극복을 위한 비상한 계획과 행동",
            "content": "1.코로나 피해 손실보상 50조원 플러스 알파 지원<br>기존에 약속드린 손실보상 50조원에 구애받지 않고, 충분하고 확실하게 보상<br>자영업자 등, 기존의 손실에 더해 앞으로 발생할 손실까지 포함하는 과감한 보상 방안 추진<br>선보상제도 도입. 입증 자료 확인 전이라도 국세청과 지자체가 보유한 행정자료를 근거로 피해액의 절반을 먼저 지원<br>2.사회 각 분야 재건을 위한 기금 50조원 이상 조성<br>50조원 이상의 기금을 마련해 코로나 이후 산업과 교육, 문화 생태계 등 사회 각 분야가 다시 살아날 수 있도록 신속하고 과감하게 지원<br>3.코로나 피해자에 과감한 금융지원 실시<br>자영업자와 소상공인, 중소기업의 기존 대출금에 대한 만기를 충분하게 연장<br> 세금, 공과금, 임대료, 인건비 등에 대해서도 적극적인 세제지원, 금융지원 등을 통해 기존 지원제도의 사각지대 제거<br> 4.IMF 긴급구제식 채무재조정 방안 적극 추진<br>소액 채무의 경우 원금 감면 폭을 현재 70%에서 90%까지 확대<br> 상황이 악화될 경우, 자영업자의 부실(우려)채무를 일괄적으로 매입하여 관리<br>예를 들면, 현재 캠코 재원으로 계획된 최대 2조원의 채권매입 사업 규모 두 배 이상 확대<br>또한 부실이 전면적으로 발생하는 상황까지 악화되면, IMF 당시의 부실채권정리기금과 유사한 기금설치 검토<br>5.코로나 극복과 회복을 위한 특별회계 설치<br> 피해지원 및 손실보상 확대, 채무 재조정, 회복 프로그램 등 각종 정부 대책을 재정적으로 뒷받침하기 위하여 과감한 재정개혁과 함께 ‘코로나 극복 및 회복지원 특별회계'를 설치하여 한시적 운영<br>6.코로나 극복과 회복 국민참여기구 운영<br>임기 개시와 동시에 대통령 직속 ‘코로나 긴급구조 특별본부’를 신설하여 긴급 구조플랜을 신속하고 과감하게 집행<br>피해 관련 데이터를 투명하게 공개하고, 소상공인 등 피해 당사자들을 의사결정 과정에 참여시킬 것",
            "image": "",
            "url": "https://www.wikiyoon.com/1855325a-76c8-4603-ad5b-aa1681afc74e"
        }


    ],
    "5": [{
            "title": "북한의 완전한 비핵화 실현",
            "content": "",
            "image": "https://oopy.lazyrockets.com/api/v2/notion/image?src=https%3A%2F%2Fs3-us-west-2.amazonaws.com%2Fsecure.notion-static.com%2Ffd1046ab-8eaa-480a-8d82-e981614b44ad%2FUntitled.png&blockId=05ca18a6-8f3f-44c4-a19a-95b5cac83c22",
            "url": "https://www.wikiyoon.com/7c410d7f-e119-4e47-b94e-0233bf5bcd59"
        },
        {
            "title": "남북관계 정상화하고 공동번영 추진",
            "content": "",
            "image": "https://oopy.lazyrockets.com/api/v2/notion/image?src=https%3A%2F%2Fs3-us-west-2.amazonaws.com%2Fsecure.notion-static.com%2Ffd1046ab-8eaa-480a-8d82-e981614b44ad%2FUntitled.png&blockId=05ca18a6-8f3f-44c4-a19a-95b5cac83c22",
            "url": "https://www.wikiyoon.com/7c410d7f-e119-4e47-b94e-0233bf5bcd59"
        },
        {
            "title": "국민합의에 기초한 통일방안 충실히 추진",
            "content": "",
            "image": "https://oopy.lazyrockets.com/api/v2/notion/image?src=https%3A%2F%2Fs3-us-west-2.amazonaws.com%2Fsecure.notion-static.com%2Ffd1046ab-8eaa-480a-8d82-e981614b44ad%2FUntitled.png&blockId=05ca18a6-8f3f-44c4-a19a-95b5cac83c22",
            "url": "https://www.wikiyoon.com/7c410d7f-e119-4e47-b94e-0233bf5bcd59"
        },
        {
            "title": "'북한인권재단’ 조속히 설립'",
            "content": "",
            "image": "https://oopy.lazyrockets.com/api/v2/notion/image?src=https%3A%2F%2Fs3-us-west-2.amazonaws.com%2Fsecure.notion-static.com%2Ffd1046ab-8eaa-480a-8d82-e981614b44ad%2FUntitled.png&blockId=05ca18a6-8f3f-44c4-a19a-95b5cac83c22",
            "url": "https://www.wikiyoon.com/7c410d7f-e119-4e47-b94e-0233bf5bcd59"
        },
        {
            "title": "한미동맹 재건하고 ‘포괄적 전략동맹’ 강화",
            "content": "",
            "image": "https://oopy.lazyrockets.com/api/v2/notion/image?src=https%3A%2F%2Fs3-us-west-2.amazonaws.com%2Fsecure.notion-static.com%2Ffd1046ab-8eaa-480a-8d82-e981614b44ad%2FUntitled.png&blockId=05ca18a6-8f3f-44c4-a19a-95b5cac83c22",
            "url": "https://www.wikiyoon.com/7c410d7f-e119-4e47-b94e-0233bf5bcd59"
        },
        {
            "title": "‘상호존중 기반한 한·중관계’ 구현",
            "content": "",
            "image": "https://oopy.lazyrockets.com/api/v2/notion/image?src=https%3A%2F%2Fs3-us-west-2.amazonaws.com%2Fsecure.notion-static.com%2Ffd1046ab-8eaa-480a-8d82-e981614b44ad%2FUntitled.png&blockId=05ca18a6-8f3f-44c4-a19a-95b5cac83c22",
            "url": "https://www.wikiyoon.com/7c410d7f-e119-4e47-b94e-0233bf5bcd59"
        },
        {
            "title": "한일 ‘김대중-오부치 선언 2.0 시대’ 실현",
            "content": "",
            "image": "https://oopy.lazyrockets.com/api/v2/notion/image?src=https%3A%2F%2Fs3-us-west-2.amazonaws.com%2Fsecure.notion-static.com%2Ffd1046ab-8eaa-480a-8d82-e981614b44ad%2FUntitled.png&blockId=05ca18a6-8f3f-44c4-a19a-95b5cac83c22",
            "url": "https://www.wikiyoon.com/7c410d7f-e119-4e47-b94e-0233bf5bcd59"
        },
        {
            "title": "한러 협력의 미래 지평 확대",
            "content": "",
            "image": "https://oopy.lazyrockets.com/api/v2/notion/image?src=https%3A%2F%2Fs3-us-west-2.amazonaws.com%2Fsecure.notion-static.com%2Ffd1046ab-8eaa-480a-8d82-e981614b44ad%2FUntitled.png&blockId=05ca18a6-8f3f-44c4-a19a-95b5cac83c22",
            "url": "https://www.wikiyoon.com/7c410d7f-e119-4e47-b94e-0233bf5bcd59"
        },
        {
            "title": "지역별로 특화된 ‘글로벌 협력 네트워크’ 구축",
            "content": "",
            "image": "https://oopy.lazyrockets.com/api/v2/notion/image?src=https%3A%2F%2Fs3-us-west-2.amazonaws.com%2Fsecure.notion-static.com%2Ffd1046ab-8eaa-480a-8d82-e981614b44ad%2FUntitled.png&blockId=05ca18a6-8f3f-44c4-a19a-95b5cac83c22",
            "url": "https://www.wikiyoon.com/7c410d7f-e119-4e47-b94e-0233bf5bcd59"
        },
        {
            "title": "경제안보 외교 적극화 ",
            "content": "",
            "image": "https://oopy.lazyrockets.com/api/v2/notion/image?src=https%3A%2F%2Fs3-us-west-2.amazonaws.com%2Fsecure.notion-static.com%2Ffd1046ab-8eaa-480a-8d82-e981614b44ad%2FUntitled.png&blockId=05ca18a6-8f3f-44c4-a19a-95b5cac83c22",
            "url": "https://www.wikiyoon.com/7c410d7f-e119-4e47-b94e-0233bf5bcd59"
        },
        {
            "title": "총리실 직속 신흥안보위원회(ESC) 설치",
            "content": "",
            "image": "https://oopy.lazyrockets.com/api/v2/notion/image?src=https%3A%2F%2Fs3-us-west-2.amazonaws.com%2Fsecure.notion-static.com%2Ffd1046ab-8eaa-480a-8d82-e981614b44ad%2FUntitled.png&blockId=05ca18a6-8f3f-44c4-a19a-95b5cac83c22",
            "url": "https://www.wikiyoon.com/7c410d7f-e119-4e47-b94e-0233bf5bcd59"
        },
        {
            "title": "‘국격에 걸맞는 글로벌 기여 외교’ 실천",
            "content": "",
            "image": "https://oopy.lazyrockets.com/api/v2/notion/image?src=https%3A%2F%2Fs3-us-west-2.amazonaws.com%2Fsecure.notion-static.com%2Ffd1046ab-8eaa-480a-8d82-e981614b44ad%2FUntitled.png&blockId=05ca18a6-8f3f-44c4-a19a-95b5cac83c22",
            "url": "https://www.wikiyoon.com/7c410d7f-e119-4e47-b94e-0233bf5bcd59"
        },
        {
            "title": "‘재외동포청’ 새로이 설치",
            "content": "",
            "image": "https://oopy.lazyrockets.com/api/v2/notion/image?src=https%3A%2F%2Fs3-us-west-2.amazonaws.com%2Fsecure.notion-static.com%2Ffd1046ab-8eaa-480a-8d82-e981614b44ad%2FUntitled.png&blockId=05ca18a6-8f3f-44c4-a19a-95b5cac83c22",
            "url": "https://www.wikiyoon.com/7c410d7f-e119-4e47-b94e-0233bf5bcd59"
        },
        {
            "title": "사이버안보 위협 대처 능력 제고",
            "content": "",
            "image": "https://oopy.lazyrockets.com/api/v2/notion/image?src=https%3A%2F%2Fs3-us-west-2.amazonaws.com%2Fsecure.notion-static.com%2Ffd1046ab-8eaa-480a-8d82-e981614b44ad%2FUntitled.png&blockId=05ca18a6-8f3f-44c4-a19a-95b5cac83c22",
            "url": "https://www.wikiyoon.com/7c410d7f-e119-4e47-b94e-0233bf5bcd59"
        },
        {
            "title": "원전 수출 외교 적극 주력",
            "content": "",
            "image": "https://oopy.lazyrockets.com/api/v2/notion/image?src=https%3A%2F%2Fs3-us-west-2.amazonaws.com%2Fsecure.notion-static.com%2Ffd1046ab-8eaa-480a-8d82-e981614b44ad%2FUntitled.png&blockId=05ca18a6-8f3f-44c4-a19a-95b5cac83c22",
            "url": "https://www.wikiyoon.com/7c410d7f-e119-4e47-b94e-0233bf5bcd59"
        },
        {
            "title": "‘AI 과학기술 강군’ 육성",
            "content": "",
            "image": "https://oopy.lazyrockets.com/api/v2/notion/image?src=https%3A%2F%2Fs3-us-west-2.amazonaws.com%2Fsecure.notion-static.com%2Ffd1046ab-8eaa-480a-8d82-e981614b44ad%2FUntitled.png&blockId=05ca18a6-8f3f-44c4-a19a-95b5cac83c22",
            "url": "https://www.wikiyoon.com/7c410d7f-e119-4e47-b94e-0233bf5bcd59"
        },
        {
            "title": "한미 군사동맹 강화, 북핵·미사일 위협 강력 대응",
            "content": "",
            "image": "https://oopy.lazyrockets.com/api/v2/notion/image?src=https%3A%2F%2Fs3-us-west-2.amazonaws.com%2Fsecure.notion-static.com%2Ffd1046ab-8eaa-480a-8d82-e981614b44ad%2FUntitled.png&blockId=05ca18a6-8f3f-44c4-a19a-95b5cac83c22",
            "url": "https://www.wikiyoon.com/7c410d7f-e119-4e47-b94e-0233bf5bcd59"
        },
        {
            "title": "'미래세대에 맞는 병영체계’ 구축",
            "content": "",
            "image": "https://oopy.lazyrockets.com/api/v2/notion/image?src=https%3A%2F%2Fs3-us-west-2.amazonaws.com%2Fsecure.notion-static.com%2Ffd1046ab-8eaa-480a-8d82-e981614b44ad%2FUntitled.png&blockId=05ca18a6-8f3f-44c4-a19a-95b5cac83c22",
            "url": "https://www.wikiyoon.com/7c410d7f-e119-4e47-b94e-0233bf5bcd59"
        },
        {
            "title": "‘민군상생 복합타운’ 건설",
            "content": "",
            "image": "https://oopy.lazyrockets.com/api/v2/notion/image?src=https%3A%2F%2Fs3-us-west-2.amazonaws.com%2Fsecure.notion-static.com%2Ffd1046ab-8eaa-480a-8d82-e981614b44ad%2FUntitled.png&blockId=05ca18a6-8f3f-44c4-a19a-95b5cac83c22",
            "url": "https://www.wikiyoon.com/7c410d7f-e119-4e47-b94e-0233bf5bcd59"
        },
        {
            "title": "'국가를 위해 희생한 분들이 분노하지 않는 나라’ 실현",
            "content": "",
            "image": "https://oopy.lazyrockets.com/api/v2/notion/image?src=https%3A%2F%2Fs3-us-west-2.amazonaws.com%2Fsecure.notion-static.com%2Ffd1046ab-8eaa-480a-8d82-e981614b44ad%2FUntitled.png&blockId=05ca18a6-8f3f-44c4-a19a-95b5cac83c22",
            "url": "https://www.wikiyoon.com/7c410d7f-e119-4e47-b94e-0233bf5bcd59"
        }

    ],
    "6": [{
            "title": "화석연료 발전 비중, 임기내 3분의 1 감축",
            "content": "ㆍ탈원전 백지화 및 탈석탄 일정 앞당겨<br>ㆍ미세먼지 감축계획 및 실천 의무화",
            "image": "https://oopy.lazyrockets.com/api/v2/notion/image?src=https%3A%2F%2Fs3-us-west-2.amazonaws.com%2Fsecure.notion-static.com%2F964d7dec-c21c-493b-8e40-6a5299144df3%2FUntitled.png&blockId=68e19a9a-10e1-48d7-8f15-83e288ef74d6",
            "url": "https://www.wikiyoon.com/c7700eb5-aae0-48a1-8451-f070a577b126"
        },
        {
            "title": "초중고, 노인요양시설에 미세먼지·바이러스 정화기 설치",
            "content": "ㆍ지하철역 등 다중이용시설 실내공기 기준 대폭 강화",
            "image": "https://oopy.lazyrockets.com/api/v2/notion/image?src=https%3A%2F%2Fs3-us-west-2.amazonaws.com%2Fsecure.notion-static.com%2F964d7dec-c21c-493b-8e40-6a5299144df3%2FUntitled.png&blockId=68e19a9a-10e1-48d7-8f15-83e288ef74d6",
            "url": "https://www.wikiyoon.com/c7700eb5-aae0-48a1-8451-f070a577b126"
        },
        {
            "title": "고농도 초미세먼지 경고, '12시간 전 발령’에서 ‘2일 전 발령’으로",
            "content": "ㆍ외출·옥외작업 일정 조정 하도록 사전 비상예방조치 강화",
            "image": "https://oopy.lazyrockets.com/api/v2/notion/image?src=https%3A%2F%2Fs3-us-west-2.amazonaws.com%2Fsecure.notion-static.com%2F964d7dec-c21c-493b-8e40-6a5299144df3%2FUntitled.png&blockId=68e19a9a-10e1-48d7-8f15-83e288ef74d6",
            "url": "https://www.wikiyoon.com/c7700eb5-aae0-48a1-8451-f070a577b126"
        },
        {
            "title": "신축 건물에 분쇄기(디스포저) 설치해 음식물쓰레기 감축",
            "content": "ㆍ건물 하부에 파쇄물 수거용기 설치해 바이오가스 생산에 활용",
            "image": "https://oopy.lazyrockets.com/api/v2/notion/image?src=https%3A%2F%2Fs3-us-west-2.amazonaws.com%2Fsecure.notion-static.com%2F625f1863-596b-416b-b423-7859336c8d4c%2FUntitled.png&blockId=0b5b26e4-6e0c-427a-afad-1eddac5a594e",
            "url": "https://www.wikiyoon.com/c7700eb5-aae0-48a1-8451-f070a577b126"
        },
        {
            "title": "매립·소각 중심에서 열분해 중심으로 쓰레기 처리방식 전환",
            "content": "ㆍ과거 재활용 불가했던 쓰레기도 재활용하는 시스템 구축<br>부착상표, 뚜껑 등 분리 배출 불편함 해소<br>폐플라스틱 열분해로 제품제조 원료나 연료로 사용",
            "image": "https://oopy.lazyrockets.com/api/v2/notion/image?src=https%3A%2F%2Fs3-us-west-2.amazonaws.com%2Fsecure.notion-static.com%2F625f1863-596b-416b-b423-7859336c8d4c%2FUntitled.png&blockId=0b5b26e4-6e0c-427a-afad-1eddac5a594e",
            "url": "https://www.wikiyoon.com/c7700eb5-aae0-48a1-8451-f070a577b126"
        }

    ],
    "7": [

    ],
    "8": [

    ],
    "9": [

    ],
    "10": [

    ],
    "11": [

    ],
    "12": [

    ],
    "13": [

    ],
    "14": [

    ],
    "15": [

    ],
    "16": [

    ],
    "17": [

    ],
    "18": [

    ],
    "19": [

    ],
    "20": [

    ]

}